Workbook

Sheet Parâmetros
A1: Plano de metas por loja — parâmetros
A2: Células em azul são entradas editáveis. As demais são calculadas.
A4: Meta de manutenção (loja na mediana do cluster ou acima) | B4: 0.02
A5: Captura do gap até a mediana do cluster | B5: 0.25
A6: Gap mínimo para prioridade "Ação" | B6: 0.1
A7: Compromisso de crescimento da rede | B7: 0.05
A8: Teto de meta por loja | B8: 0.2
A10: Calibração
A11: Crescimento ponderado com as metas iniciais | B11: =SUMPRODUCT('Metas por Loja'!$J$2:$J$1116,'Metas por Loja'!$K$2:$K$1116)/SUM('Metas por Loja'!$J$2:$J$1116) -> 0.041903316
A12: Fator sem teto (iteração 0) | B12: =B7/B11 -> 1.193223
A13: Fator com teto (iteração 1) | B13: =($B$7*SUM('Metas por Loja'!$J$2:$J$1116)-$B$8*SUMPRODUCT('Metas por Loja'!$J$2:$J$1116,--('Metas por Loja'!$K$2:$K$1116*B12>$B$8)))/SUMPRODUCT('Metas por Loja'!$J$2:$J$1116,'Metas por Loja'!$K$2:$K$1116,--('Metas por Loja'!$K$2:$K$1116*B12<=$B$8)) -> 1.2201678
A14: Fator com teto (iteração 2) | B14: =($B$7*SUM('Metas por Loja'!$J$2:$J$1116)-$B$8*SUMPRODUCT('Metas por Loja'!$J$2:$J$1116,--('Metas por Loja'!$K$2:$K$1116*B13>$B$8)))/SUMPRODUCT('Metas por Loja'!$J$2:$J$1116,'Metas por Loja'!$K$2:$K$1116,--('Metas por Loja'!$K$2:$K$1116*B13<=$B$8)) -> 1.2201917
A15: Fator com teto (iteração 3) | B15: =($B$7*SUM('Metas por Loja'!$J$2:$J$1116)-$B$8*SUMPRODUCT('Metas por Loja'!$J$2:$J$1116,--('Metas por Loja'!$K$2:$K$1116*B14>$B$8)))/SUMPRODUCT('Metas por Loja'!$J$2:$J$1116,'Metas por Loja'!$K$2:$K$1116,--('Metas por Loja'!$K$2:$K$1116*B14<=$B$8)) -> 1.2201917
A16: Fator com teto (iteração 4) | B16: =($B$7*SUM('Metas por Loja'!$J$2:$J$1116)-$B$8*SUMPRODUCT('Metas por Loja'!$J$2:$J$1116,--('Metas por Loja'!$K$2:$K$1116*B15>$B$8)))/SUMPRODUCT('Metas por Loja'!$J$2:$J$1116,'Metas por Loja'!$K$2:$K$1116,--('Metas por Loja'!$K$2:$K$1116*B15<=$B$8)) -> 1.2201917
A17: Fator com teto (iteração 5) | B17: =($B$7*SUM('Metas por Loja'!$J$2:$J$1116)-$B$8*SUMPRODUCT('Metas por Loja'!$J$2:$J$1116,--('Metas por Loja'!$K$2:$K$1116*B16>$B$8)))/SUMPRODUCT('Metas por Loja'!$J$2:$J$1116,'Metas por Loja'!$K$2:$K$1116,--('Metas por Loja'!$K$2:$K$1116*B16<=$B$8)) -> 1.2201917
A18: Fator com teto (iteração 6) | B18: =($B$7*SUM('Metas por Loja'!$J$2:$J$1116)-$B$8*SUMPRODUCT('Metas por Loja'!$J$2:$J$1116,--('Metas por Loja'!$K$2:$K$1116*B17>$B$8)))/SUMPRODUCT('Metas por Loja'!$J$2:$J$1116,'Metas por Loja'!$K$2:$K$1116,--('Metas por Loja'!$K$2:$K$1116*B17<=$B$8)) -> 1.2201917
A19: Fator de calibração final | B19: =B18 -> 1.2201917
A20: Convergiu? (iterações 5 e 6 iguais) | B20: =IF(ABS(B18-B17)<0.0000001,"Sim","Não") -> Sim
A21: Meta de manutenção após calibração | B21: =B4*B19 -> 0.024403834
A22: Lojas no teto | B22: =SUMPRODUCT(--('Metas por Loja'!$K$2:$K$1116*B19>B8)) -> 47
A23: Média simples das metas iniciais | B23: =AVERAGE('Metas por Loja'!$K$2:$K$1116) -> 0.051459827
A24: Média simples das metas finais | B24: =AVERAGE('Metas por Loja'!$G$2:$G$1116) -> 0.060543041
A25: Crescimento ponderado com as metas finais (checagem) | B25: =SUMPRODUCT('Metas por Loja'!$J$2:$J$1116,'Metas por Loja'!$G$2:$G$1116)/SUM('Metas por Loja'!$J$2:$J$1116) -> 0.05
A26: Faturamento anual estimado da rede (R$) | B26: =SUM('Metas por Loja'!$J$2:$J$1116) -> 2.3456693e+09
A27: Ganho anual previsto com as metas finais (R$) | B27: =B25*B26 -> 1.1728346e+08
A31: Benchmark por cluster (mediana da venda média por dia)
A32: Cluster | B32: Nome do Cluster | C32: Benchmark do Grupo (R$/dia)
A33: 0 | B33: Bairro competitivo de cesta pequena | C33: {=MEDIAN(IF('Metas por Loja'!$B$2:$B$1116=A33,'Metas por Loja'!$D$2:$D$1116))} -> 5476.3703
A34: 1 | B34: Destino de cesta grande | C34: {=MEDIAN(IF('Metas por Loja'!$B$2:$B$1116=A34,'Metas por Loja'!$D$2:$D$1116))} -> 6959.9244
A35: 2 | B35: Sazonal | C35: {=MEDIAN(IF('Metas por Loja'!$B$2:$B$1116=A35,'Metas por Loja'!$D$2:$D$1116))} -> 6324.801
A36: 3 | B36: Dependente de promoção | C36: {=MEDIAN(IF('Metas por Loja'!$B$2:$B$1116=A36,'Metas por Loja'!$D$2:$D$1116))} -> 5909.2449
A37: 4 | B37: Alto fluxo, cesta pequena | C37: {=MEDIAN(IF('Metas por Loja'!$B$2:$B$1116=A37,'Metas por Loja'!$D$2:$D$1116))} -> 8837.1051

Sheet Metas por Loja
A1: Loja | B1: Cluster | C1: Nome do Cluster | D1: Venda Média por Dia (R$) | E1: Benchmark do Grupo (R$/dia) | F1: Gap Percentual | G1: Meta Percentual | H1: Prioridade | I1: Dias de Operação por Ano | J1: Faturamento Anual (R$) | K1: Meta Inicial (antes da calibração) | L1: Meta de Venda por Dia (R$) | M1: Abre aos Domingos | N1: Permanência no Cluster | O1: Observação
A2: 1 | B2: 0 | C2: Bairro competitivo de cesta pequena | D2: 4759.096 | E2: =INDEX(Parâmetros!$C$33:$C$37,MATCH(B2,Parâmetros!$A$33:$A$37,0)) -> 5476.3703 | F2: =MAX(0,(E2-D2)/D2) -> 0.1507165 | G2: =MIN(K2*Parâmetros!$B$19,Parâmetros!$B$8) -> 0.07037959 | H2: =IF(F2>=Parâmetros!$B$6,"Ação","Acompanhamento") -> Ação | I2: 302.61677 | J2: =D2*I2 -> 1440182.3 | K2: =Parâmetros!$B$4+Parâmetros!$B$5*F2 -> 0.057679125 | L2: =D2*(1+G2) -> 5094.0393 | M2: 0 | N2: 0.77631579 | O2: =IF(AND(B2=4,M2=1),IF(N2<0.8,"Subgrupo 7 dias; fronteira de cluster","Subgrupo 7 dias"),IF(N2<0.8,"Fronteira de cluster","")) -> Fronteira de cluster
A3: 2 | B3: 0 | C3: Bairro competitivo de cesta pequena | D3: 4953.9005 | E3: =INDEX(Parâmetros!$C$33:$C$37,MATCH(B3,Parâmetros!$A$33:$A$37,0)) -> 5476.3703 | F3: =MAX(0,(E3-D3)/D3) -> 0.10546635 | G3: =MIN(K3*Parâmetros!$B$19,Parâmetros!$B$8) -> 0.056576126 | H3: =IF(F3>=Parâmetros!$B$6,"Ação","Acompanhamento") -> Ação | I3: 303.77919 | J3: =D3*I3 -> 1504891.9 | K3: =Parâmetros!$B$4+Parâmetros!$B$5*F3 -> 0.046366588 | L3: =D3*(1+G3) -> 5234.173 | M3: 0 | N3: 0.98684211 | O3: =IF(AND(B3=4,M3=1),IF(N3<0.8,"Subgrupo 7 dias; fronteira de cluster","Subgrupo 7 dias"),IF(N3<0.8,"Fronteira de cluster",""))
A4: 3 | B4: 3 | C4: Dependente de promoção | D4: 6942.5687 | E4: =INDEX(Parâmetros!$C$33:$C$37,MATCH(B4,Parâmetros!$A$33:$A$37,0)) -> 5909.2449 | F4: =MAX(0,(E4-D4)/D4) -> 0 | G4: =MIN(K4*Parâmetros!$B$19,Parâmetros!$B$8) -> 0.024403834 | H4: =IF(F4>=Parâmetros!$B$6,"Ação","Acompanhamento") -> Acompanhamento | I4: 301.84183 | J4: =D4*I4 -> 2095557.6 | K4: =Parâmetros!$B$4+Parâmetros!$B$5*F4 -> 0.02 | L4: =D4*(1+G4) -> 7111.994 | M4: 0 | N4: 1 | O4: =IF(AND(B4=4,M4=1),IF(N4<0.8,"Subgrupo 7 dias; fronteira de cluster","Subgrupo 7 dias"),IF(N4<0.8,"Fronteira de cluster",""))
A5: 4 | B5: 4 | C5: Alto fluxo, cesta pequena | D5: 9638.4018 | E5: =INDEX(Parâmetros!$C$33:$C$37,MATCH(B5,Parâmetros!$A$33:$A$37,0)) -> 8837.1051 | F5: =MAX(0,(E5-D5)/D5) -> 0 | G5: =MIN(K5*Parâmetros!$B$19,Parâmetros!$B$8) -> 0.024403834 | H5: =IF(F5>=Parâmetros!$B$6,"Ação","Acompanhamento") -> Acompanhamento | I5: 303.77919 | J5: =D5*I5 -> 2927945.9 | K5: =Parâmetros!$B$4+Parâmetros!$B$5*F5 -> 0.02 | L5: =D5*(1+G5) -> 9873.6157 | M5: 0 | N5: 1 | O5: =IF(AND(B5=4,M5=1),IF(N5<0.8,"Subgrupo 7 dias; fronteira de cluster","Subgrupo 7 dias"),IF(N5<0.8,"Fronteira de cluster",""))
A6: 5 | B6: 3 | C6: Dependente de promoção | D6: 4676.2747 | E6: =INDEX(Parâmetros!$C$33:$C$37,MATCH(B6,Parâmetros!$A$33:$A$37,0)) -> 5909.2449 | F6: =MAX(0,(E6-D6)/D6) -> 0.26366504 | G6: =MIN(K6*Parâmetros!$B$19,Parâmetros!$B$8) -> 0.10483431 | H6: =IF(F6>=Parâmetros!$B$6,"Ação","Acompanhamento") -> Ação | I6: 301.84183 | J6: =D6*I6 -> 1411495.3 | K6: =Parâmetros!$B$4+Parâmetros!$B$5*F6 -> 0.08591626 | L6: =D6*(1+G6) -> 5166.5087 | M6: 0 | N6: 1 | O6: =IF(AND(B6=4,M6=1),IF(N6<0.8,"Subgrupo 7 dias; fronteira de cluster","Subgrupo 7 dias"),IF(N6<0.8,"Fronteira de cluster",""))
A7: 6 | B7: 0 | C7: Bairro competitivo de cesta pequena | D7: 5509.9462 | E7: =INDEX(Parâmetros!$C$33:$C$37,MATCH(B7,Parâmetros!$A$33:$A$37,0)) -> 5476.3703 | F7: =MAX(0,(E7-D7)/D7) -> 0 | G7: =MIN(K7*Parâmetros!$B$19,Parâmetros!$B$8) -> 0.024403834 | H7: =IF(F7>=Parâmetros!$B$6,"Ação","Acompanhamento") -> Acompanhamento | I7: 302.2293 | J7: =D7*I7 -> 1665267.2 | K7: =Parâmetros!$B$4+Parâmetros!$B$5*F7 -> 0.02 | L7: =D7*(1+G7) -> 5644.41 | M7: 0 | N7: 1 | O7: =IF(AND(B7=4,M7=1),IF(N7<0.8,"Subgrupo 7 dias; fronteira de cluster","Subgrupo 7 dias"),IF(N7<0.8,"Fronteira de cluster",""))
A8: 7 | B8: 1 | C8: Destino de cesta grande | D8: 8817.0509 | E8: =INDEX(Parâmetros!$C$33:$C$37,MATCH(B8,Parâmetros!$A$33:$A$37,0)) -> 6959.9244 | F8: =MAX(0,(E8-D8)/D8) -> 0 | G8: =MIN(K8*Parâmetros!$B$19,Parâmetros!$B$8) -> 0.024403834 | H8: =IF(F8>=Parâmetros!$B$6,"Ação","Acompanhamento") -> Acompanhamento | I8: 304.55414 | J8: =D8*I8 -> 2685269.4 | K8: =Parâmetros!$B$4+Parâmetros!$B$5*F8 -> 0.02 | L8: =D8*(1+G8) -> 9032.2207 | M8: 0 | N8: 1 | O8: =IF(AND(B8=4,M8=1),IF(N8<0.8,"Subgrupo 7 dias; fronteira de cluster","Subgrupo 7 dias"),IF(N8<0.8,"Fronteira de cluster",""))
A9: 8 | B9: 3 | C9: Dependente de promoção | D9: 5539.3584 | E9: =INDEX(Parâmetros!$C$33:$C$37,MATCH(B9,Parâmetros!$A$33:$A$37,0)) -> 5909.2449 | F9: =MAX(0,(E9-D9)/D9) -> 0.066774241 | G9: =MIN(K9*Parâmetros!$B$19,Parâmetros!$B$8) -> 0.044773178 | H9: =IF(F9>=Parâmetros!$B$6,"Ação","Acompanhamento") -> Acompanhamento | I9: 303.77919 | J9: =D9*I9 -> 1682741.8 | K9: =Parâmetros!$B$4+Parâmetros!$B$5*F9 -> 0.03669356 | L9: =D9*(1+G9) -> 5787.3731 | M9: 0 | N9: 1 | O9: =IF(AND(B9=4,M9=1),IF(N9<0.8,"Subgrupo 7 dias; fronteira de cluster","Subgrupo 7 dias"),IF(N9<0.8,"Fronteira de cluster",""))
A10: 9 | B10: 1 | C10: Destino de cesta grande | D10: 6562.3376 | E10: =INDEX(Parâmetros!$C$33:$C$37,MATCH(B10,Parâmetros!$A$33:$A$37,0)) -> 6959.9244 | F10: =MAX(0,(E10-D10)/D10) -> 0.060586145 | G10: =MIN(K10*Parâmetros!$B$19,Parâmetros!$B$8) -> 0.042885512 | H10: =IF(F10>=Parâmetros!$B$6,"Ação","Acompanhamento") -> Acompanhamento | I10: 301.84183 | J10: =D10*I10 -> 1980788 | K10: =Parâmetros!$B$4+Parâmetros!$B$5*F10 -> 0.035146536 | L10: =D10*(1+G10) -> 6843.7668 | M10: 0 | N10: 1 | O10: =IF(AND(B10=4,M10=1),IF(N10<0.8,"Subgrupo 7 dias; fronteira de cluster","Subgrupo 7 dias"),IF(N10<0.8,"Fronteira de cluster",""))
A11: 10 | B11: 1 | C11: Destino de cesta grande | D11: 5568.4209 | E11: =INDEX(Parâmetros!$C$33:$C$37,MATCH(B11,Parâmetros!$A$33:$A$37,0)) -> 6959.9244 | F11: =MAX(0,(E11-D11)/D11) -> 0.24989193 | G11: =MIN(K11*Parâmetros!$B$19,Parâmetros!$B$8) -> 0.10063285 | H11: =IF(F11>=Parâmetros!$B$6,"Ação","Acompanhamento") -> Ação | I11: 303.77919 | J11: =D11*I11 -> 1691570.4 | K11: =Parâmetros!$B$4+Parâmetros!$B$5*F11 -> 0.082472982 | L11: =D11*(1+G11) -> 6128.787 | M11: 0 | N11: 0.77777778 | O11: =IF(AND(B11=4,M11=1),IF(N11<0.8,"Subgrupo 7 dias; fronteira de cluster","Subgrupo 7 dias"),IF(N11<0.8,"Fronteira de cluster","")) -> Fronteira de cluster
A12: 11 | B12: 2 | C12: Sazonal | D12: 8030.977 | E12: =INDEX(Parâmetros!$C$33:$C$37,MATCH(B12,Parâmetros!$A$33:$A$37,0)) -> 6324.801 | F12: =MAX(0,(E12-D12)/D12) -> 0 | G12: =MIN(K12*Parâmetros!$B$19,Parâmetros!$B$8) -> 0.024403834 | H12: =IF(F12>=Parâmetros!$B$6,"Ação","Acompanhamento") -> Acompanhamento | I12: 303.77919 | J12: =D12*I12 -> 2439643.7 | K12: =Parâmetros!$B$4+Parâmetros!$B$5*F12 -> 0.02 | L12: =D12*(1+G12) -> 8226.9637 | M12: 0 | N12: 1 | O12: =IF(AND(B12=4,M12=1),IF(N12<0.8,"Subgrupo 7 dias; fronteira de cluster","Subgrupo 7 dias"),IF(N12<0.8,"Fronteira de cluster",""))
A13: 12 | B13: 0 | C13: Bairro competitivo de cesta pequena | D13: 7589.5982 | E13: =INDEX(Parâmetros!$C$33:$C$37,MATCH(B13,Parâmetros!$A$33:$A$37,0)) -> 5476.3703 | F13: =MAX(0,(E13-D13)/D13) -> 0 | G13: =MIN(K13*Parâmetros!$B$19,Parâmetros!$B$8) -> 0.024403834 | H13: =IF(F13>=Parâmetros!$B$6,"Ação","Acompanhamento") -> Acompanhamento | I13: 303.77919 | J13: =D13*I13 -> 2305562 | K13: =Parâmetros!$B$4+Parâmetros!$B$5*F13 -> 0.02 | L13: =D13*(1+G13) -> 7774.8135 | M13: 0 | N13: 0.96296296 | O13: =IF(AND(B13=4,M13=1),IF(N13<0.8,"Subgrupo 7 dias; fronteira de cluster","Subgrupo 7 dias"),IF(N13<0.8,"Fronteira de cluster",""))
... A1116: 1115 | B1116: 1 | C1116: Destino de cesta grande | D1116: 6302.4699 | E1116: =INDEX(Parâmetros!$C$33:$C$37,MATCH(B1116,Parâmetros!$A$33:$A$37,0)) -> 6959.9244 | F1116: =MAX(0,(E1116-D1116)/D1116) -> 0.10431695 | G1116: =MIN(K1116*Parâmetros!$B$19,Parâmetros!$B$8) -> 0.056225503 | H1116: =IF(F1116>=Parâmetros!$B$6,"Ação","Acompanhamento") -> Ação | I1116: 302.61677 | J1116: =D1116*I1116 -> 1907233.1 | K1116: =Parâmetros!$B$4+Parâmetros!$B$5*F1116 -> 0.046079238 | L1116: =D1116*(1+G1116) -> 6656.8295 | M1116: 0 | N1116: 1 | O1116: =IF(AND(B1116=4,M1116=1),IF(N1116<0.8,"Subgrupo 7 dias; fronteira de cluster","Subgrupo 7 dias"),IF(N1116<0.8,"Fronteira de cluster",""))

Sheet Resumo por Cluster
A1: Resumo do plano por cluster
A3: Cluster | B3: Nome do Cluster | C3: Lojas | D3: Lojas em Ação | E3: Benchmark (R$/dia) | F3: Meta Média | G3: Meta Máxima | H3: Crescimento Ponderado | I3: Faturamento Anual (R$)
A4: =Parâmetros!A33 -> 0 | B4: =Parâmetros!B33 -> Bairro competitivo de cesta pequena | C4: =COUNTIF('Metas por Loja'!$B$2:$B$1116,A4) -> 292 | D4: =COUNTIFS('Metas por Loja'!$B$2:$B$1116,A4,'Metas por Loja'!$H$2:$H$1116,"Ação") -> 106 | E4: =Parâmetros!C33 -> 5476.3703 | F4: =AVERAGEIF('Metas por Loja'!$B$2:$B$1116,A4,'Metas por Loja'!$G$2:$G$1116) -> 0.058575146 | G4: {=MAX(IF('Metas por Loja'!$B$2:$B$1116=A4,'Metas por Loja'!$G$2:$G$1116))} -> 0.2 | H4: =SUMPRODUCT(('Metas por Loja'!$B$2:$B$1116=A4)*'Metas por Loja'!$J$2:$J$1116*'Metas por Loja'!$G$2:$G$1116)/I4 -> 0.048667334 | I4: =SUMIF('Metas por Loja'!$B$2:$B$1116,A4,'Metas por Loja'!$J$2:$J$1116) -> 5.0498464e+08
A5: =Parâmetros!A34 -> 1 | B5: =Parâmetros!B34 -> Destino de cesta grande | C5: =COUNTIF('Metas por Loja'!$B$2:$B$1116,A5) -> 414 | D5: =COUNTIFS('Metas por Loja'!$B$2:$B$1116,A5,'Metas por Loja'!$H$2:$H$1116,"Ação") -> 152 | E5: =Parâmetros!C34 -> 6959.9244 | F5: =AVERAGEIF('Metas por Loja'!$B$2:$B$1116,A5,'Metas por Loja'!$G$2:$G$1116) -> 0.0583384 | G5: {=MAX(IF('Metas por Loja'!$B$2:$B$1116=A5,'Metas por Loja'!$G$2:$G$1116))} -> 0.2 | H5: =SUMPRODUCT(('Metas por Loja'!$B$2:$B$1116=A5)*'Metas por Loja'!$J$2:$J$1116*'Metas por Loja'!$G$2:$G$1116)/I5 -> 0.049340722 | I5: =SUMIF('Metas por Loja'!$B$2:$B$1116,A5,'Metas por Loja'!$J$2:$J$1116) -> 8.8457145e+08
A6: =Parâmetros!A35 -> 2 | B6: =Parâmetros!B35 -> Sazonal | C6: =COUNTIF('Metas por Loja'!$B$2:$B$1116,A6) -> 65 | D6: =COUNTIFS('Metas por Loja'!$B$2:$B$1116,A6,'Metas por Loja'!$H$2:$H$1116,"Ação") -> 25 | E6: =Parâmetros!C35 -> 6324.801 | F6: =AVERAGEIF('Metas por Loja'!$B$2:$B$1116,A6,'Metas por Loja'!$G$2:$G$1116) -> 0.071037726 | G6: {=MAX(IF('Metas por Loja'!$B$2:$B$1116=A6,'Metas por Loja'!$G$2:$G$1116))} -> 0.2 | H6: =SUMPRODUCT(('Metas por Loja'!$B$2:$B$1116=A6)*'Metas por Loja'!$J$2:$J$1116*'Metas por Loja'!$G$2:$G$1116)/I6 -> 0.056558274 | I6: =SUMIF('Metas por Loja'!$B$2:$B$1116,A6,'Metas por Loja'!$J$2:$J$1116) -> 1.2631911e+08
A7: =Parâmetros!A36 -> 3 | B7: =Parâmetros!B36 -> Dependente de promoção | C7: =COUNTIF('Metas por Loja'!$B$2:$B$1116,A7) -> 165 | D7: =COUNTIFS('Metas por Loja'!$B$2:$B$1116,A7,'Metas por Loja'!$H$2:$H$1116,"Ação") -> 64 | E7: =Parâmetros!C36 -> 5909.2449 | F7: =AVERAGEIF('Metas por Loja'!$B$2:$B$1116,A7,'Metas por Loja'!$G$2:$G$1116) -> 0.06293062 | G7: {=MAX(IF('Metas por Loja'!$B$2:$B$1116=A7,'Metas por Loja'!$G$2:$G$1116))} -> 0.2 | H7: =SUMPRODUCT(('Metas por Loja'!$B$2:$B$1116=A7)*'Metas por Loja'!$J$2:$J$1116*'Metas por Loja'!$G$2:$G$1116)/I7 -> 0.05046315 | I7: =SUMIF('Metas por Loja'!$B$2:$B$1116,A7,'Metas por Loja'!$J$2:$J$1116) -> 3.0565975e+08
A8: =Parâmetros!A37 -> 4 | B8: =Parâmetros!B37 -> Alto fluxo, cesta pequena | C8: =COUNTIF('Metas por Loja'!$B$2:$B$1116,A8) -> 179 | D8: =COUNTIFS('Metas por Loja'!$B$2:$B$1116,A8,'Metas por Loja'!$H$2:$H$1116,"Ação") -> 70 | E8: =Parâmetros!C37 -> 8837.1051 | F8: =AVERAGEIF('Metas por Loja'!$B$2:$B$1116,A8,'Metas por Loja'!$G$2:$G$1116) -> 0.062840479 | G8: {=MAX(IF('Metas por Loja'!$B$2:$B$1116=A8,'Metas por Loja'!$G$2:$G$1116))} -> 0.2 | H8: =SUMPRODUCT(('Metas por Loja'!$B$2:$B$1116=A8)*'Metas por Loja'!$J$2:$J$1116*'Metas por Loja'!$G$2:$G$1116)/I8 -> 0.050545953 | I8: =SUMIF('Metas por Loja'!$B$2:$B$1116,A8,'Metas por Loja'!$J$2:$J$1116) -> 5.241343e+08
A9: Rede | B9: — | C9: =SUM(C4:C8) -> 1115 | D9: =SUM(D4:D8) -> 417 | E9: =MEDIAN('Metas por Loja'!D2:D1116) -> 6589.9485 | F9: =AVERAGE('Metas por Loja'!G2:G1116) -> 0.060543041 | G9: =MAX('Metas por Loja'!G2:G1116) -> 0.2 | H9: =Parâmetros!B25 -> 0.05 | I9: =SUM(I4:I8) -> 2.3456693e+09
A12: Distribuição das metas finais
A13: Faixa | B13: De | C13: Até | D13: Lojas | E13: % das lojas
A14: Manutenção | B14: 0 | C14: =Parâmetros!B21+0.00001 -> 0.024413834 | D14: =COUNTIFS('Metas por Loja'!$G$2:$G$1116,">"&B14,'Metas por Loja'!$G$2:$G$1116,"<="&C14) -> 559 | E14: =D14/COUNT('Metas por Loja'!$G$2:$G$1116) -> 0.50134529
A15: Manutenção a 5% | B15: =C14 -> 0.024413834 | C15: 0.05 | D15: =COUNTIFS('Metas por Loja'!$G$2:$G$1116,">"&B15,'Metas por Loja'!$G$2:$G$1116,"<="&C15) -> 117 | E15: =D15/COUNT('Metas por Loja'!$G$2:$G$1116) -> 0.10493274
A16: 5% a 10% | B16: 0.05 | C16: 0.1 | D16: =COUNTIFS('Metas por Loja'!$G$2:$G$1116,">"&B16,'Metas por Loja'!$G$2:$G$1116,"<="&C16) -> 214 | E16: =D16/COUNT('Metas por Loja'!$G$2:$G$1116) -> 0.19192825
A17: 10% a 15% | B17: 0.1 | C17: 0.15 | D17: =COUNTIFS('Metas por Loja'!$G$2:$G$1116,">"&B17,'Metas por Loja'!$G$2:$G$1116,"<="&C17) -> 121 | E17: =D17/COUNT('Metas por Loja'!$G$2:$G$1116) -> 0.10852018
A18: 15% a 20% | B18: 0.15 | C18: =Parâmetros!B8-0.00001 -> 0.19999 | D18: =COUNTIFS('Metas por Loja'!$G$2:$G$1116,">"&B18,'Metas por Loja'!$G$2:$G$1116,"<="&C18) -> 57 | E18: =D18/COUNT('Metas por Loja'!$G$2:$G$1116) -> 0.051121076
A19: No teto | B19: =C18 -> 0.19999 | C19: 1 | D19: =COUNTIFS('Metas por Loja'!$G$2:$G$1116,">"&B19,'Metas por Loja'!$G$2:$G$1116,"<="&C19) -> 47 | E19: =D19/COUNT('Metas por Loja'!$G$2:$G$1116) -> 0.042152466
A20: Total | D20: =SUM(D14:D19) -> 1115 | E20: =SUM(E14:E19) -> 1

Sheet Premissas
A1: Premissas do plano de metas
A3: 1. Referência de desempenho: venda média por dia de operação (dias abertos com faturamento > 0), histórico de 01/2013 a 07/2015.
A4: 2. Benchmark do grupo: mediana da venda média por dia das lojas do mesmo cluster (K-Means, k = 5).
A5: 3. Gap percentual: crescimento que a loja precisa para chegar ao benchmark = (benchmark - venda) / venda; zero para quem está na mediana ou acima.
A6: 4. Meta inicial: manutenção para quem está na mediana ou acima; manutenção + captura x gap para quem está abaixo.
A7: 5. Calibração: todas as metas multiplicadas pelo mesmo fator, com teto por loja (padrão 20%). O fator é recalculado por iteração para compensar o que o teto corta, e a rede cresce exatamente o compromisso ponderado pelo faturamento anual.
A8: 6. Faturamento anual da loja: venda média por dia x dias de operação por ano (proporção de dias abertos no histórico x 365).
A9: 7. Prioridade: "Ação" para lojas com gap igual ou acima do limiar; "Acompanhamento" para as demais.
A10: 8. As metas são de faturamento, não de margem; não consideram custo de promoção, canibalização ou mudança de preço.
A11: 9. Observação: "Subgrupo 7 dias" marca as lojas do cluster 4 que abrem aos domingos (perfil de conveniência, ticket bem abaixo do resto do cluster); "Fronteira de cluster" marca as lojas que ficaram no próprio cluster em menos de 80% das subamostras do teste de estabilidade. A meta dessas lojas deve ser revisada com o gestor.
A12: 10. Para mudar a regra, altere as células em azul da aba Parâmetros; toda a planilha é recalculada.
